cxmeta/__init__.py
cxmeta/config/__init__.py
cxmeta/config/config_loader.py
cxmeta/config/project.py
cxmeta/pipeline/__init__.py
cxmeta/pipeline/builder.py
cxmeta/pipeline/combiner.py
cxmeta/pipeline/cxx_processor.py
cxmeta/pipeline/gfm_exporter.py
cxmeta/pipeline/rst_processor.py
cxmeta/pipeline/source_module.py
cxmeta/pipeline/stream.py
cxmeta/tools/__init__.py
cxmeta/tools/cli.py
cxmeta/tools/driver.py
cxmeta-1.0.0a0.data/scripts/cli.py
test/__init__.py
test/simple-module.md
test/test_basics.py
test/test_build_pipeline.py
test/test_combiner.py
test/test_comments.py
test/test_ghm_exporter.py
test/test_macros.py
test/test_statements.py
cxmeta-1.0.0a0.dist-info/LICENSE
cxmeta-1.0.0a0.dist-info/METADATA
cxmeta-1.0.0a0.dist-info/WHEEL
cxmeta-1.0.0a0.dist-info/entry_points.txt
cxmeta-1.0.0a0.dist-info/top_level.txt
cxmeta-1.0.0a0.dist-info/RECORD
